pandalyze/__init__.py
pandalyze/analyze.py
pandalyze/config/__init__.py
pandalyze/config/operation_targets_config.py
pandalyze/detectantipatterns.py
pandalyze/models/__init__.py
pandalyze/models/anti_pattern_model.py
pandalyze/models/operation_targets.py
pandalyze/profiler.py
pandalyze/rules/anti_pattern_rules.py
pandalyze/warnings.py
pandalyze-0.1.5.dist-info/METADATA
pandalyze-0.1.5.dist-info/WHEEL
pandalyze-0.1.5.dist-info/RECORD
