Metadata-Version: 2.3
Name: pandalyze
Version: 0.1.5
Summary: pandalyze is a pandas analyzer that allows developers to use pandas more efficiently
Author: MoAkbarally
Author-email: mo.akbarally@gmail.com
Requires-Python: >=3.9,<4.0
Classifier: Programming Language :: Python :: 3
Classifier: Programming Language :: Python :: 3.10
Classifier: Programming Language :: Python :: 3.11
Classifier: Programming Language :: Python :: 3.12
Classifier: Programming Language :: Python :: 3.13
Requires-Dist: pandas (>=2.3.2,<3.0.0)
Requires-Dist: psutil (>=7.0.0,<8.0.0)
Requires-Dist: rich (>=14.1.0,<15.0.0)
